nonebot_plugin_tetris_stats/__init__.py
nonebot_plugin_tetris_stats/version.py
nonebot_plugin_tetris_stats/config/config.py
nonebot_plugin_tetris_stats/config/migrations/09d4bb60160d_rename_field.py
nonebot_plugin_tetris_stats/config/migrations/0d50142b780f_add_field.py
nonebot_plugin_tetris_stats/config/migrations/2ff388a8c486_add_verify_field.py
nonebot_plugin_tetris_stats/config/migrations/3588702dd3a4_modify_field_length.py
nonebot_plugin_tetris_stats/config/migrations/3c25a5a8c050_refactor_historical.py
nonebot_plugin_tetris_stats/config/migrations/3d900bb0e8d4_migrate_nonebot_plugin_tetris_stats_.py
nonebot_plugin_tetris_stats/config/migrations/405c6936a164_migrate_nonebot_plugin_tetris_stats_.py
nonebot_plugin_tetris_stats/config/migrations/5a1b93948494_add_tetrioleaguestats.py
nonebot_plugin_tetris_stats/config/migrations/612d8b00d9ac_create_a_new_table.py
nonebot_plugin_tetris_stats/config/migrations/6c3206f90cc3_add_field.py
nonebot_plugin_tetris_stats/config/migrations/766cc7e75a62_migrate_to_uninfo.py
nonebot_plugin_tetris_stats/config/migrations/8459b2a4b7a3_migrate_nonebot_plugin_tetris_stats_.py
nonebot_plugin_tetris_stats/config/migrations/8a91210ce14d_correct_the_data_in_historicaldata.py
nonebot_plugin_tetris_stats/config/migrations/9866f53ce44f_init_db.py
nonebot_plugin_tetris_stats/config/migrations/9cd1647db502_merge_old_db.py
nonebot_plugin_tetris_stats/config/migrations/9f6582279ce2_recreate_historical_data.py
nonebot_plugin_tetris_stats/config/migrations/__init__.py
nonebot_plugin_tetris_stats/config/migrations/a1195e989cc6_add_tetrio_user_configuration.py
nonebot_plugin_tetris_stats/config/migrations/b15844837693_migrate_to_nonobot_plugin_user.py
nonebot_plugin_tetris_stats/config/migrations/b2075a5ce371_create_new_tables.py
nonebot_plugin_tetris_stats/config/migrations/b7fbdafc339a_add_user_unique_identifier_field_to_.py
nonebot_plugin_tetris_stats/config/migrations/b96c8c18b79a_migrate_nonebot_plugin_tetris_stats_.py
nonebot_plugin_tetris_stats-1.11.0.dist-info/METADATA
nonebot_plugin_tetris_stats-1.11.0.dist-info/WHEEL
nonebot_plugin_tetris_stats-1.11.0.dist-info/licenses/LICENSE
nonebot_plugin_tetris_stats-1.11.0.dist-info/RECORD
