Metadata-Version: 2.4
Name: nonebot-plugin-tetris-stats
Version: 1.11.0
Summary: 一款基于 NoneBot2 的用于查询 Tetris 相关游戏数据的插件
Project-URL: Homepage, https://github.com/A-Minos/nonebot-plugin-tetris-stats
Project-URL: Repository, https://github.com/A-Minos/nonebot-plugin-tetris-stats
Project-URL: Issues, https://github.com/A-Minos/nonebot-plugin-tetris-stats/issues
Author-email: shoucandanghehe <wallfjjd@gmail.com>
License-File: LICENSE
Keywords: nonebot2
Classifier: Programming Language :: Python :: 3 :: Only
Classifier: Programming Language :: Python :: 3.10
Classifier: Programming Language :: Python :: 3.11
Classifier: Programming Language :: Python :: 3.12
Classifier: Programming Language :: Python :: 3.13
Requires-Python: >=3.10
Requires-Dist: aiocache>=0.12.3
Requires-Dist: aiofiles>=24.1.0
Requires-Dist: arclet-alconna<2
Requires-Dist: async-lru>=2.0.4
Requires-Dist: fake-useragent>=2.0.3
Requires-Dist: httpx>=0.27.2
Requires-Dist: jinja2>=3.1.4
Requires-Dist: lxml>=5.3.0
Requires-Dist: msgspec>=0.18.6
Requires-Dist: nonebot-plugin-alconna>=0.53.1
Requires-Dist: nonebot-plugin-apscheduler>=0.5.0
Requires-Dist: nonebot-plugin-localstore>=0.7.1
Requires-Dist: nonebot-plugin-orm>=0.7.6
Requires-Dist: nonebot-plugin-uninfo>=0.7.4
Requires-Dist: nonebot-plugin-user>=0.4.4
Requires-Dist: nonebot-plugin-waiter>=0.8.0
Requires-Dist: nonebot-session-to-uninfo>=0.0.2
Requires-Dist: nonebot2[fastapi]>=2.3.3
Requires-Dist: pandas>=2.2.3
Requires-Dist: pillow>=11.0.0
Requires-Dist: playwright>=1.48.0
Requires-Dist: rich>=13.9.3
Requires-Dist: strenum>=0.4.15
Requires-Dist: yarl>=1.16.0
